{
  "photos": [
    {
      "id": 3,
      "title": "image 3",
      "url": "http://placehold.it/600/771796",
      "thumbnailUrl": "http://placehold.it/150/771796",
      "author": "typicode"
    },
    {
      "id": 4,
      "title": "image 4",
      "url": "http://placehold.it/600/771796",
      "thumbnailUrl": "http://placehold.it/150/771796",
      "author": "typicode"
    },
    {
      "id": 5,
      "title": "image 5",
      "url": "http://placehold.it/600/771796",
      "thumbnailUrl": "http://placehold.it/150/771796",
      "author": "typicode"
    }
  ],
  "teamprofileimages": [
    {
      "id": 1,
      "title": "profile image 1",
      "thumbnailUrl": "src/images/profile_thumbs/batman_thumb.jpg",
      "url": "src/images/profile_images/batman_profile.jpg",
      "author": "batman"
    },
    {
      "id": 2,
      "title": "profile image 2",
      "thumbnailUrl": "src/images/profile_thumbs/daredevil_thumb.jpg",
      "url": "src/images/profile_images/daredevil_profile.jpg",
      "author": "daredevil"
    },
    {
      "id": 3,
      "title": "profile image 3",
      "thumbnailUrl": "src/images/profile_thumbs/gambit_thumb.jpg",
      "url": "src/images/profile_images/gambit_profile.jpg",
      "author": "gambit"
    },
    {
      "id": 4,
      "title": "profile image 4",
      "thumbnailUrl": "src/images/profile_thumbs/nightwing_thumb.jpg",
      "url": "src/images/profile_images/nightwing_profile.jpg",
      "author": "nightwing"
    },
    {
      "id": 5,
      "title": "profile image 5",
      "thumbnailUrl": "src/images/profile_thumbs/wolverine_thumb.jpg",
      "url": "src/images/profile_images/wolverine_profile.jpg",
      "author": "wolverine"
    },
    {
      "id": 6,
      "title": "profile thumb 6",
      "thumbnailUrl": "src/images/profile_thumbs/hellboy_thumb.jpg",
      "url": "src/images/profile_images/hellboy_profile.jpg",
      "author": "hellboy"
    }
  ],
  "teamprofiletext": [
    {
      "id": 1,
      "pretitle": "pretitle",
      "title": "title",
      "subtitle": "subtitle"
    }
  ],
  "posts": [
    {
      "id": 1,
      "title": "json-server",
      "author": "typicode"
    }
  ],
  "comments": [
    {
      "id": 1,
      "body": "some comment",
      "postId": 1
    }
  ],
  "profile": {
    "name": "typicode"
  }
}